README.md
setup.py
DTAnalyze/Activation.py
DTAnalyze/TreeAnalysis.c
DTAnalyze/__init__.py
DTAnalyze.egg-info/PKG-INFO
DTAnalyze.egg-info/SOURCES.txt
DTAnalyze.egg-info/dependency_links.txt
DTAnalyze.egg-info/top_level.txt