Metadata-Version: 2.1
Name: DTAnalyze
Version: 1.0
Summary: Python Decision Tree Analysis
Home-page: https://github.com/nicholastoddsmith/DTAnalyze
Author: Nicholas T. Smith
Author-email: nicholastsmithblog@gmail.com
License: UNKNOWN
Keywords: Decision,Tree,RandomForest,GBM,Activation
Platform: UNKNOWN
Classifier: Intended Audience :: Education
Classifier: Intended Audience :: Science/Research
Classifier: Topic :: Scientific/Engineering
Classifier: Topic :: Scientific/Engineering :: Mathematics
Classifier: Natural Language :: English
Classifier: Operating System :: OS Independent
Classifier: Programming Language :: C
Classifier: Programming Language :: Cython
Classifier: Programming Language :: Python
Classifier: Programming Language :: Python :: 3
